tesscentroidvetting/__init__.py
tesscentroidvetting/tesscentroidvetting.py
tesscentroidvetting/tessprfmodel.py
tesscentroidvetting/version.py
tesscentroidvetting-1.4.0.dist-info/licenses/LICENSE
tesscentroidvetting-1.4.0.dist-info/METADATA
tesscentroidvetting-1.4.0.dist-info/WHEEL
tesscentroidvetting-1.4.0.dist-info/top_level.txt
tesscentroidvetting-1.4.0.dist-info/RECORD
