Metadata-Version: 2.4
Name: tesscentroidvetting
Version: 1.4.0
Summary: TESS Centroid Vetting
Author-email: Rafael Rodrigues <rafael.rodrgs@gmail.com>
Project-URL: Homepage, https://github.com/exo-pt/TESS-Centroid_vetting
Keywords: TESS,centroids,exoplanets,PRF,vetting,transits,python
Classifier: Programming Language :: Python :: 3
Classifier: License :: OSI Approved :: MIT License
Classifier: Topic :: Scientific/Engineering :: Astronomy
License-File: LICENSE
Requires-Dist: numpy
Requires-Dist: matplotlib
Requires-Dist: astropy
Requires-Dist: astroquery
Requires-Dist: scipy
Requires-Dist: lightkurve
Dynamic: license-file
